CHANGELOG
COPYRIGHT
INSTALL
LICENSE
MANIFEST.in
README
connection.xml
setup.py
tryton.cfg
./__init__.py
./connection.py
./connection.xml
./tryton.cfg
./locale/bg_BG.po
./locale/ca_ES.po
./locale/cs_CZ.po
./locale/de_DE.po
./locale/es_AR.po
./locale/es_CO.po
./locale/es_ES.po
./locale/fr_FR.po
./locale/nl_NL.po
./locale/ru_RU.po
./locale/sl_SI.po
./tests/__init__.py
./tests/test_ldap_connection.py
./view/connection_form.xml
./view/test_connection_result_form.xml
locale/bg_BG.po
locale/ca_ES.po
locale/cs_CZ.po
locale/de_DE.po
locale/es_AR.po
locale/es_CO.po
locale/es_ES.po
locale/fr_FR.po
locale/nl_NL.po
locale/ru_RU.po
locale/sl_SI.po
trytond_ldap_connection.egg-info/PKG-INFO
trytond_ldap_connection.egg-info/SOURCES.txt
trytond_ldap_connection.egg-info/dependency_links.txt
trytond_ldap_connection.egg-info/entry_points.txt
trytond_ldap_connection.egg-info/not-zip-safe
trytond_ldap_connection.egg-info/requires.txt
trytond_ldap_connection.egg-info/top_level.txt
view/connection_form.xml
view/test_connection_result_form.xml